txt2mobi3/__init__.py
txt2mobi3/txt2html3.py
txt2mobi3/txt2mobi3.py
txt2mobi3/txt2mobi3_clt.py
txt2mobi3/txt2mobi3_config.py
txt2mobi3/txt2mobi3_exceptions.py
txt2mobi3/resources/img/default_cover.png
txt2mobi3/resources/kindlegen/linux/kindlegen
txt2mobi3/resources/kindlegen/mac/kindlegen
txt2mobi3/resources/kindlegen/win32/kindlegen.exe
txt2mobi3-0.2.12.dist-info/LICENSE
txt2mobi3-0.2.12.dist-info/METADATA
txt2mobi3-0.2.12.dist-info/WHEEL
txt2mobi3-0.2.12.dist-info/entry_points.txt
txt2mobi3-0.2.12.dist-info/top_level.txt
txt2mobi3-0.2.12.dist-info/RECORD
