Metadata-Version: 2.1
Name: txt2mobi3
Version: 0.2.12
Summary: Convert Chinese novel txt files into Kindle mobi files.
Home-page: https://github.com/renweizhukov/txt2mobi3
Author: Wei Ren
Author-email: renwei2004@gmail.com
License: UNKNOWN
Project-URL: Source, https://github.com/renweizhukov/txt2mobi3
Project-URL: Documentation, https://github.com/renweizhukov/txt2mobi3
Project-URL: Bug Reports, https://github.com/renweizhukov/txt2mobi3/issues
Keywords: txt mobi python3
Platform: UNKNOWN
Classifier: Development Status :: 4 - Beta
Classifier: Intended Audience :: End Users/Desktop
Classifier: Topic :: Text Processing :: General
Classifier: License :: OSI Approved :: GNU General Public License v3 (GPLv3)
Classifier: Programming Language :: Python :: 3
Requires-Python: >=3
Requires-Dist: chardet
Requires-Dist: setuptools
